{
  "AUGUST 2024": [
    {
      "id": 1,
      "Title": "AUGUST 2024",
      "typelogo": "https://www.mancity.com/meta/media/re5mofgu/microsoftteams-image-43.png",
      "date": "Wed 28 Aug",
      "typetext": "Friendly",
      "HomeName": "Manchester City",
      "Homelogo": "https://www.mancity.com/meta/media/yzscd2rf/manchester_city_fc_badge.png",
      "AwayName": "Leicester City",
      "Awaylogo": "https://www.mancity.com/meta/media/tualebgx/leicester.png",
      "Time": "19:15",
      "Sub": "HBF Park, Perth, Australia - 28th August 18:15 AWST",
      "Ticket": "Tickets Available",
      "TicketBtn": "BUY NOW"
    }
  ],
  "SEPTEMBER 2024": [
    {
      "id": 2,
      "Title": "SEPTEMBER 2024",
      "typelogo": "https://www.mancity.com/meta/media/re5mofgu/microsoftteams-image-43.png",
      "date": "Sun 01 Sep",
      "typetext": "Friendly",
      "HomeName": "Manchester City",
      "Homelogo": "https://www.mancity.com/meta/media/yzscd2rf/manchester_city_fc_badge.png",
      "AwayName": "Opponents TBC",
      "Awaylogo": "https://www.mancity.com/meta/media/mk0lv1ql/tbc-crest-question-mark.png",
      "Time": "08:00",
      "Sub": "Optus Stadium, Perth, Australia - 1st September",
      "Ticket": "Tickets Available",
      "TicketBtn": "BUY NOW"
    },
    {
      "id": 3,
      "Title": "SEPTEMBER 2024",
      "typelogo": "https://www.mancity.com/meta/media/21uhpayu/bwsl_master_vertical_badge_rgb.png",
      "date": "Sun 01 Sep",
      "typetext": "Barclays WSL",
      "HomeName": "Arsenal",
      "Homelogo": "https://www.mancity.com/meta/media/lmtfrilx/arsenal.png",
      "AwayName": "Manchester City",
      "Awaylogo": "https://www.mancity.com/meta/media/yzscd2rf/manchester_city_fc_badge.png",
      "Time": "20:30",
      "Sub": "",
      "Ticket": "Coming soon",
      "TicketBtn": ""
    },
    {
      "id": 4,
      "Title": "SEPTEMBER 2024",
      "typelogo": "https://www.mancity.com/meta/media/21uhpayu/bwsl_master_vertical_badge_rgb.png",
      "date": "Sun 01 Sep",
      "typetext": "Barclays WSL",
      "HomeName": "Manchester City",
      "Homelogo": "https://www.mancity.com/meta/media/yzscd2rf/manchester_city_fc_badge.png",
      "AwayName": "Brighton and HoveAlbion",
      "Awaylogo": "https://www.mancity.com/meta/media/pwinp3vk/brighton.png",
      "Time": "20:30",
      "Sub": "",
      "Ticket": "Coming soon",
      "TicketBtn": ""
    }
  ],
  "OCTOBER 2024": [
    {
      "id": 5,
      "Title": "SEPTEMBER 2024",
      "typelogo": "https://www.mancity.com/meta/media/21uhpayu/bwsl_master_vertical_badge_rgb.png",
      "date": "Sun 06 Oct",
      "typetext": "Barclays WSL",
      "HomeName": "Manchester City",
      "Homelogo": "https://www.mancity.com/meta/media/yzscd2rf/manchester_city_fc_badge.png",
      "AwayName": "West Ham United",
      "Awaylogo": "https://www.mancity.com/meta/media/vxuduons/west_ham_united.png",
      "Time": "22:00",
      "Sub": "Fixture date and time to be confirmed.",
      "Ticket": "Coming soon",
      "TicketBtn": ""
    },
    {
      "id": 6,
      "Title": "SEPTEMBER 2024",
      "typelogo": "https://www.mancity.com/meta/media/21uhpayu/bwsl_master_vertical_badge_rgb.png",
      "date": "Sun 13 Sep",
      "typetext": "Barclays WSL",
      "HomeName": "Liverpool",
      "Homelogo": "https://www.mancity.com/meta/media/5e0pzxke/liverpool.png",
      "AwayName": "Manchester City",
      "Awaylogo": "https://www.mancity.com/meta/media/yzscd2rf/manchester_city_fc_badge.png",
      "Time": "22:00",
      "Sub": "Fixture date and time to be confirmed.",
      "Ticket": "Coming soon",
      "TicketBtn": ""
    },
    {
      "id": 7,
      "Title": "SEPTEMBER 2024",
      "typelogo": "https://www.mancity.com/meta/media/21uhpayu/bwsl_master_vertical_badge_rgb.png",
      "date": "Sun 20 Oct",
      "typetext": "Barclays WSL",
      "HomeName": "Manchester City",
      "Homelogo": "https://www.mancity.com/meta/media/yzscd2rf/manchester_city_fc_badge.png",
      "AwayName": "Aston Villa",
      "Awaylogo": "https://www.mancity.com/meta/media/klbh3x01/a-villa-new-full.png",
      "Time": "22:00",
      "Sub": "Fixture date and time to be confirmed.",
      "Ticket": "Coming soon",
      "TicketBtn": ""
    }
  ],
  "NOVEMBER 2024": [
    {
      "id": 8,
      "Title": "SEPTEMBER 2024",
      "typelogo": "https://www.mancity.com/meta/media/21uhpayu/bwsl_master_vertical_badge_rgb.png",
      "date": "Sun 03 Nov",
      "typetext": "Barclays WSL",
      "HomeName": "Crystal Palace",
      "Homelogo": "https://www.mancity.com/meta/media/ttda4o0h/cpalace.png",
      "AwayName": "Manchester City",
      "Awaylogo": "https://www.mancity.com/meta/media/yzscd2rf/manchester_city_fc_badge.png",
      "Time": "23:00",
      "Sub": "Fixture date and time to be confirmed.",
      "Ticket": "Coming soon",
      "TicketBtn": ""
    },
    {
      "id": 9,
      "Title": "SEPTEMBER 2024",
      "typelogo": "https://www.mancity.com/meta/media/21uhpayu/bwsl_master_vertical_badge_rgb.png",
      "date": "Sun 10 Nov",
      "typetext": "Barclays WSL",
      "HomeName": "Manchester City",
      "Homelogo": "https://www.mancity.com/meta/media/yzscd2rf/manchester_city_fc_badge.png",
      "AwayName": "Tottenham Hotspur",
      "Awaylogo": "https://www.mancity.com/meta/media/t02jppxo/spurs-logo-with-outline.png",
      "Time": "23:00",
      "Sub": "Fixture date and time to be confirmed.",
      "Ticket": "Coming soon",
      "TicketBtn": ""
    },
    {
      "id": 10,
      "Title": "SEPTEMBER 2024",
      "typelogo": "https://www.mancity.com/meta/media/21uhpayu/bwsl_master_vertical_badge_rgb.png",
      "date": "Sun 17 Nov",
      "typetext": "Barclays WSL",
      "HomeName": "Chelsea",
      "Homelogo": "https://www.mancity.com/meta/media/bbbbljr5/chelsea.png",
      "AwayName": "Manchester City",
      "Awaylogo": "https://www.mancity.com/meta/media/yzscd2rf/manchester_city_fc_badge.png",
      "Time": "23:00",
      "Sub": "Fixture date and time to be confirmed.",
      "Ticket": "Coming soon",
      "TicketBtn": ""
    }
  ],
  "DECEMBER 2024": [
    {
      "id": 11,
      "Title": "SEPTEMBER 2024",
      "typelogo": "https://www.mancity.com/meta/media/21uhpayu/bwsl_master_vertical_badge_rgb.png",
      "date": "Sun 08 Dec",
      "typetext": "Barclays WSL",
      "HomeName": "Manchester City",
      "Homelogo": "https://www.mancity.com/meta/media/yzscd2rf/manchester_city_fc_badge.png",
      "AwayName": "Leicester City",
      "Awaylogo": "https://www.mancity.com/meta/media/tualebgx/leicester.png",
      "Time": "23:00",
      "Sub": "Fixture date and time to be confirmed.",
      "Ticket": "Coming soon",
      "TicketBtn": ""
    },
    {
      "id": 12,
      "Title": "SEPTEMBER 2024",
      "typelogo": "https://www.mancity.com/meta/media/21uhpayu/bwsl_master_vertical_badge_rgb.png",
      "date": "Sun 15 Dec",
      "typetext": "Barclays WSL",
      "HomeName": "Everton",
      "Homelogo": "https://www.mancity.com/meta/media/2vujb1uo/everton.png",
      "AwayName": "Manchester City",
      "Awaylogo": "https://www.mancity.com/meta/media/yzscd2rf/manchester_city_fc_badge.png",
      "Time": "23:00",
      "Sub": "Fixture date and time to be confirmed.",
      "Ticket": "Coming soon",
      "TicketBtn": ""
    }
  ],
  "JANUARY 2025": [
    {
      "id": 13,
      "Title": "SEPTEMBER 2024",
      "typelogo": "https://www.mancity.com/meta/media/21uhpayu/bwsl_master_vertical_badge_rgb.png",
      "date": "Sun 19 Jan",
      "typetext": "Barclays WSL",
      "HomeName": "Manchester City",
      "Homelogo": "https://www.mancity.com/meta/media/yzscd2rf/manchester_city_fc_badge.png",
      "AwayName": "Manchester United",
      "Awaylogo": "https://www.mancity.com/meta/media/d1zedbrg/manunited.png",
      "Time": "23:00",
      "Sub": "Fixture date and time to be confirmed.",
      "Ticket": "Coming soon",
      "TicketBtn": ""
    },
    {
      "id": 14,
      "Title": "SEPTEMBER 2024",
      "typelogo": "https://www.mancity.com/meta/media/21uhpayu/bwsl_master_vertical_badge_rgb.png",
      "date": "Sun 26 Jan",
      "typetext": "Barclays WSL",
      "HomeName": "Aston Villa",
      "Homelogo": "https://www.mancity.com/meta/media/klbh3x01/a-villa-new-full.png",
      "AwayName": "Manchester City",
      "Awaylogo": "https://www.mancity.com/meta/media/yzscd2rf/manchester_city_fc_badge.png",
      "Time": "23:00",
      "Sub": "Fixture date and time to be confirmed.",
      "Ticket": "Coming soon",
      "TicketBtn": ""
    }
  ],
  "FEBRUARY 2025": [
    {
      "id": 15,
      "Title": "SEPTEMBER 2024",
      "typelogo": "https://www.mancity.com/meta/media/21uhpayu/bwsl_master_vertical_badge_rgb.png",
      "date": "Sun 02 Feb",
      "typetext": "Barclays WSL",
      "HomeName": "Manchester City",
      "Homelogo": "https://www.mancity.com/meta/media/yzscd2rf/manchester_city_fc_badge.png",
      "AwayName": "Arsenal",
      "Awaylogo": "https://www.mancity.com/meta/media/lmtfrilx/arsenal.png",
      "Time": "23:00",
      "Sub": "Fixture date and time to be confirmed.",
      "Ticket": "Coming soon",
      "TicketBtn": ""
    },
    {
      "id": 16,
      "Title": "SEPTEMBER 2024",
      "typelogo": "https://www.mancity.com/meta/media/21uhpayu/bwsl_master_vertical_badge_rgb.png",
      "date": "Sun 16 Feb",
      "typetext": "Barclays WSL",
      "HomeName": "Manchester City",
      "Homelogo": "https://www.mancity.com/meta/media/yzscd2rf/manchester_city_fc_badge.png",
      "AwayName": "Liverpool",
      "Awaylogo": "https://www.mancity.com/meta/media/5e0pzxke/liverpool.png",
      "Time": "23:00",
      "Sub": "Fixture date and time to be confirmed.",
      "Ticket": "Coming soon",
      "TicketBtn": ""
    }
  ],
  "MARCH 2025": [
    {
      "id": 17,
      "Title": "SEPTEMBER 2024",
      "typelogo": "https://www.mancity.com/meta/media/21uhpayu/bwsl_master_vertical_badge_rgb.png",
      "date": "Sun 02 Mar",
      "typetext": "Barclays WSL",
      "HomeName": "Tottenham Hotspur",
      "Homelogo": "https://www.mancity.com/meta/media/t02jppxo/spurs-logo-with-outline.png",
      "AwayName": "Manchester City",
      "Awaylogo": "https://www.mancity.com/meta/media/yzscd2rf/manchester_city_fc_badge.png",
      "Time": "23:00",
      "Sub": "Fixture date and time to be confirmed.",
      "Ticket": "Coming soon",
      "TicketBtn": ""
    },
    {
      "id": 18,
      "Title": "SEPTEMBER 2024",
      "typelogo": "https://www.mancity.com/meta/media/21uhpayu/bwsl_master_vertical_badge_rgb.png",
      "date": "Sun 16 Mar",
      "typetext": "Barclays WSL",
      "HomeName": "West Ham United",
      "Homelogo": "https://www.mancity.com/meta/media/vxuduons/west_ham_united.png",
      "AwayName": "Manchester City",
      "Awaylogo": "https://www.mancity.com/meta/media/yzscd2rf/manchester_city_fc_badge.png",
      "Time": "23:00",
      "Sub": "Fixture date and time to be confirmed.",
      "Ticket": "Coming soon",
      "TicketBtn": ""
    },
    {
      "id": 19,
      "Title": "SEPTEMBER 2024",
      "typelogo": "https://www.mancity.com/meta/media/21uhpayu/bwsl_master_vertical_badge_rgb.png",
      "date": "Sun 23 Mar",
      "typetext": "Barclays WSL",
      "HomeName": "Manchester City",
      "Homelogo": "https://www.mancity.com/meta/media/yzscd2rf/manchester_city_fc_badge.png",
      "AwayName": "Chelsea",
      "Awaylogo": "https://www.mancity.com/meta/media/bbbbljr5/chelsea.png",
      "Time": "23:00",
      "Sub": "Fixture date and time to be confirmed.",
      "Ticket": "Coming soon",
      "TicketBtn": ""
    },
    {
      "id": 20,
      "Title": "SEPTEMBER 2024",
      "typelogo": "https://www.mancity.com/meta/media/21uhpayu/bwsl_master_vertical_badge_rgb.png",
      "date": "Sun 30 Mar",
      "typetext": "Barclays WSL",
      "HomeName": "Brighton and Hove Albion",
      "Homelogo": "https://www.mancity.com/meta/media/pwinp3vk/brighton.png",
      "AwayName": "Manchester City",
      "Awaylogo": "https://www.mancity.com/meta/media/yzscd2rf/manchester_city_fc_badge.png",
      "Time": "22:00",
      "Sub": "Fixture date and time to be confirmed.",
      "Ticket": "Coming soon",
      "TicketBtn": ""
    }
  ],
  "APRIL 2025": [
    {
      "id": 21,
      "Title": "SEPTEMBER 2024",
      "typelogo": "https://www.mancity.com/meta/media/21uhpayu/bwsl_master_vertical_badge_rgb.png",
      "date": "Sun 20 Apr",
      "typetext": "Barclays WSL",
      "HomeName": "Manchester City",
      "Homelogo": "https://www.mancity.com/meta/media/yzscd2rf/manchester_city_fc_badge.png",
      "AwayName": "Everton",
      "Awaylogo": "https://www.mancity.com/meta/media/2vujb1uo/everton.png",
      "Time": "22:00",
      "Sub": "Fixture date and time to be confirmed.",
      "Ticket": "Coming soon",
      "TicketBtn": ""
    },
    {
      "id": 22,
      "Title": "SEPTEMBER 2024",
      "typelogo": "https://www.mancity.com/meta/media/21uhpayu/bwsl_master_vertical_badge_rgb.png",
      "date": "Sun 27 Apr",
      "typetext": "Barclays WSL",
      "HomeName": "Leicester City",
      "Homelogo": "https://www.mancity.com/meta/media/tualebgx/leicester.png",
      "AwayName": "Manchester City",
      "Awaylogo": "https://www.mancity.com/meta/media/yzscd2rf/manchester_city_fc_badge.png",
      "Time": "22:00",
      "Sub": "Fixture date and time to be confirmed.",
      "Ticket": "Coming soon",
      "TicketBtn": ""
    }
  ],
  "MAY 2025": [
    {
      "id": 23,
      "Title": "SEPTEMBER 2024",
      "typelogo": "https://www.mancity.com/meta/media/21uhpayu/bwsl_master_vertical_badge_rgb.png",
      "date": "Sun 04 May",
      "typetext": "Barclays WSL",
      "HomeName": "Manchester United",
      "Homelogo": "https://www.mancity.com/meta/media/d1zedbrg/manunited.png",
      "AwayName": "Manchester City",
      "Awaylogo": "https://www.mancity.com/meta/media/yzscd2rf/manchester_city_fc_badge.png",
      "Time": "22:00",
      "Sub": "Fixture date and time to be confirmed.",
      "Ticket": "Coming soon",
      "TicketBtn": ""
    },
    {
      "id": 24,
      "Title": "SEPTEMBER 2024",
      "typelogo": "https://www.mancity.com/meta/media/21uhpayu/bwsl_master_vertical_badge_rgb.png",
      "date": "Sun 11 May",
      "typetext": "Barclays WSL",
      "HomeName": "Manchester City",
      "Homelogo": "https://www.mancity.com/meta/media/yzscd2rf/manchester_city_fc_badge.png",
      "AwayName": "Crystal Palace",
      "Awaylogo": "https://www.mancity.com/meta/media/ttda4o0h/cpalace.png",
      "Time": "22:00",
      "Sub": "Fixture date and time to be confirmed.",
      "Ticket": "Coming soon",
      "TicketBtn": ""
    }
  ]
}
